ussl/__init__.py
ussl/exceptions/__init__.py
ussl/exceptions/base.py
ussl/exceptions/protocol_exc.py
ussl/exceptions/validation_exc.py
ussl/model/__init__.py
ussl/postprocessing/__init__.py
ussl/postprocessing/base.py
ussl/protocol/__init__.py
ussl/protocol/base.py
ussl/protocol/ldap.py
ussl/protocol/ssh.py
ussl/protocol/winexe.py
ussl/protocol/winrm.py
ussl/protocol/wmi.py
ussl/utils/__init__.py
ussl-1.2.9.dist-info/METADATA
ussl-1.2.9.dist-info/WHEEL
ussl-1.2.9.dist-info/top_level.txt
ussl-1.2.9.dist-info/RECORD
