Metadata-Version: 2.4
Name: ussl
Version: 1.2.9
Summary: Пакет разработчиков USSC-SOC для упрощения взаимодействия с АРМ, серверами и сетевыми устройствами
Author: ussc soc dev team
Author-email: daniil.bessmertnykh@udv.group, miroslav.zenkov@udv.group
Classifier: Programming Language :: Python
Classifier: Programming Language :: Python :: 3.8
Requires-Python: >=3.8.0
Requires-Dist: pywinrm==0.4.3
Requires-Dist: paramiko==3.3.1
Requires-Dist: marshmallow==3.20.2
Requires-Dist: python-ldap==3.4.4; platform_system != "Windows"
Dynamic: author
Dynamic: author-email
Dynamic: classifier
Dynamic: description
Dynamic: description-content-type
Dynamic: requires-dist
Dynamic: requires-python
Dynamic: summary
